odoo/addons/l10n_fr_account_vat_return/README.rst
odoo/addons/l10n_fr_account_vat_return/__init__.py
odoo/addons/l10n_fr_account_vat_return/__manifest__.py
odoo/addons/l10n_fr_account_vat_return/post_install.py
odoo/addons/l10n_fr_account_vat_return/data/account_fiscal_position_template.xml
odoo/addons/l10n_fr_account_vat_return/data/ir_cron.xml
odoo/addons/l10n_fr_account_vat_return/data/l10n.fr.account.vat.box.csv
odoo/addons/l10n_fr_account_vat_return/data/mail_template.xml
odoo/addons/l10n_fr_account_vat_return/i18n/es.po
odoo/addons/l10n_fr_account_vat_return/i18n/fr.po
odoo/addons/l10n_fr_account_vat_return/i18n/l10n_fr_account_vat_return.pot
odoo/addons/l10n_fr_account_vat_return/migrations/0.0.0/pre-migration.py
odoo/addons/l10n_fr_account_vat_return/migrations/16.0.6.0.0/post-migration.py
odoo/addons/l10n_fr_account_vat_return/migrations/16.0.7.0.0/post-migration.py
odoo/addons/l10n_fr_account_vat_return/models/__init__.py
odoo/addons/l10n_fr_account_vat_return/models/account_account.py
odoo/addons/l10n_fr_account_vat_return/models/account_fiscal_position.py
odoo/addons/l10n_fr_account_vat_return/models/account_move.py
odoo/addons/l10n_fr_account_vat_return/models/account_move_line.py
odoo/addons/l10n_fr_account_vat_return/models/account_tax.py
odoo/addons/l10n_fr_account_vat_return/models/l10n_fr_account_vat_box.py
odoo/addons/l10n_fr_account_vat_return/models/l10n_fr_account_vat_return.py
odoo/addons/l10n_fr_account_vat_return/models/res_company.py
odoo/addons/l10n_fr_account_vat_return/readme/CONTRIBUTORS.rst
odoo/addons/l10n_fr_account_vat_return/readme/DESCRIPTION.rst
odoo/addons/l10n_fr_account_vat_return/report/CA3_cerfa.pdf
odoo/addons/l10n_fr_account_vat_return/security/ir.model.access.csv
odoo/addons/l10n_fr_account_vat_return/security/ir_rule.xml
odoo/addons/l10n_fr_account_vat_return/static/description/icon.png
odoo/addons/l10n_fr_account_vat_return/static/description/index.html
odoo/addons/l10n_fr_account_vat_return/tests/__init__.py
odoo_addon_l10n_fr_account_vat_return-16.0.8.0.0.3.dist-info/METADATA
odoo_addon_l10n_fr_account_vat_return-16.0.8.0.0.3.dist-info/WHEEL
odoo_addon_l10n_fr_account_vat_return-16.0.8.0.0.3.dist-info/top_level.txt
odoo_addon_l10n_fr_account_vat_return-16.0.8.0.0.3.dist-info/RECORD
