Metadata-Version: 2.1
Name: odoo-addon-l10n_fr_account_vat_return
Version: 16.0.8.0.0.3
Summary: VAT return for France: CA3, 3310-A, 3519
Home-page: https://github.com/OCA/l10n-france
Author: Akretion,Odoo Community Association (OCA)
Author-email: support@odoo-community.org
License: AGPL-3
Classifier: Programming Language :: Python
Classifier: Framework :: Odoo
Classifier: Framework :: Odoo :: 16.0
Classifier: License :: OSI Approved :: GNU Affero General Public License v3
Requires-Python: >=3.10
Requires-Dist: odoo-addon-intrastat-base<16.1dev,>=16.0dev
Requires-Dist: odoo-addon-l10n-fr-oca<16.1dev,>=16.0dev
Requires-Dist: odoo<16.1dev,>=16.0a
Requires-Dist: pypdf>=3.1.0
Requires-Dist: xlsxwriter
